12tree-0.1.0.dist-info/licenses/LICENSE
twelve_tree/__init__.py
twelve_tree/cli.py
twelve_tree/node.py
twelve_tree/tree_store.py
12tree-0.1.0.dist-info/METADATA
12tree-0.1.0.dist-info/WHEEL
12tree-0.1.0.dist-info/entry_points.txt
12tree-0.1.0.dist-info/top_level.txt
12tree-0.1.0.dist-info/RECORD
