Metadata-Version: 2.4
Name: 12tree
Version: 0.1.0
Summary: 12Tree - Efficient Floating Point Data Store with AVL Tree Indexing
Home-page: https://github.com/yourusername/12tree
Author: 12Tree Team
License: MIT
Project-URL: Homepage, https://github.com/yourusername/12tree
Project-URL: Repository, https://github.com/yourusername/12tree
Project-URL: Issues, https://github.com/yourusername/12tree/issues
Project-URL: Documentation, https://12tree.readthedocs.io/
Classifier: Development Status :: 4 - Beta
Classifier: Intended Audience :: Developers
Classifier: License :: OSI Approved :: MIT License
Classifier: Operating System :: OS Independent
Classifier: Programming Language :: Python :: 3
Classifier: Programming Language :: Python :: 3.8
Classifier: Programming Language :: Python :: 3.9
Classifier: Programming Language :: Python :: 3.10
Classifier: Programming Language :: Python :: 3.11
Classifier: Programming Language :: Python :: 3.12
Classifier: Topic :: Database
Classifier: Topic :: Software Development :: Libraries :: Python Modules
Requires-Python: >=3.8
License-File: LICENSE
Requires-Dist: typer>=0.9.0
Dynamic: home-page
Dynamic: license-file
Dynamic: requires-python
